{
    "main_title": "Форма по прибытию на участок / Участокко келген маалдагы форма",
    "identifier": "form_enter",
    "period": {
            "start": "2020-10-04 06:30:00 GMT+6",
            "finish": "2020-10-04 07:30:00 GMT+6",
            "before": {"nofill": false},
            "in": {"nofill": false},
            "after": {"nofill": true}
    },
    "questions": [
        {
            "title": "1. Я нахожусь на участке номер / Мен номер __ участогундамын:",
            "type": "input",
            "attachMaterials": true
        },
        {
            "title": "2. Я пришёл/пришла на участок в (указать время) / Мен участокко саат __ келдим:",
            "type": "time"
        }
    ]
}